ptyp/__init__.py
ptyp/_modidx.py
ptyp/_tmp.py
ptyp/atyp.py
ptyp/cons.py
ptyp/duck.py
ptyp/grds.py
ptyp/meta.py
ptyp/prot.py
ptyp/ptyp.py
ptyp/type.py
ptyp/util.py
ptyp-0.0.19.dist-info/LICENSE
ptyp-0.0.19.dist-info/METADATA
ptyp-0.0.19.dist-info/WHEEL
ptyp-0.0.19.dist-info/entry_points.txt
ptyp-0.0.19.dist-info/top_level.txt
ptyp-0.0.19.dist-info/RECORD
