Metadata-Version: 2.1
Name: ptyp
Version: 0.0.19
Summary: ptyp (prototype)
Home-page: https://github.com/dsm-72/ptyp
Author: dsm-72
Author-email: sumner.magruder@yale.edu
License: Apache Software License 2.0
Keywords: protocol prot prots prototype nbdev jupyter notebook python types type alias type ptyp typ optional opt
Classifier: Development Status :: 4 - Beta
Classifier: Intended Audience :: Developers
Classifier: Natural Language :: English
Classifier: Programming Language :: Python :: 3.11
Classifier: License :: OSI Approved :: Apache Software License
Requires-Python: >=3.11
License-File: LICENSE
Requires-Dist: nchr
Requires-Dist: nlit
Requires-Dist: astr
Requires-Dist: uscr
Requires-Dist: pdec
Requires-Dist: itry
Requires-Dist: matr
Provides-Extra: dev
